mmgui_cli/__init__.py
mmgui_cli/cli copy.py
mmgui_cli/cli.py
mmgui_cli/mmgui_cli.py
mmgui_cli/templates/base/README.md
mmgui_cli/templates/base/README.md.tpl
mmgui_cli/templates/base/requirements.txt
mmgui_cli/templates/base/core_package/__init__.py
mmgui_cli/templates/base/core_package/core.py
mmgui_cli/templates/base/gui/__init__.py
mmgui_cli/templates/base/gui/app.py
mmgui_cli/templates/base/gui/function_registry.py
mmgui_cli/templates/base/gui/functions.py
mmgui_cli/templates/base/gui/ui/index.html
mmgui_cli/templates/base/scripts/setup_dev.bat.tpl
mmgui_cli/templates/base/scripts/setup_dev.sh.tpl
mmgui_cli/templates/react cdn/index.html
mmgui_cli/templates/vue cdn/index.html
mmgui_cli-0.0.1.dist-info/licenses/LICENSE
mmgui_cli-0.0.1.dist-info/METADATA
mmgui_cli-0.0.1.dist-info/WHEEL
mmgui_cli-0.0.1.dist-info/entry_points.txt
mmgui_cli-0.0.1.dist-info/top_level.txt
mmgui_cli-0.0.1.dist-info/RECORD
