Metadata-Version: 2.4
Name: mmgui-cli
Version: 0.0.1
Summary: CLI 工具：一键生成 mmgui 桌面应用项目模板（支持 Vue CDN、React CDN、原生 HTML）
Author-email: guominzhi <mianaei@163.com>
Requires-Python: >=3.8
License-File: LICENSE
Requires-Dist: click
Requires-Dist: inquirer
Dynamic: license-file
